cfgutils/__init__.py
cfgutils/dominator.py
cfgutils/file_formats.py
cfgutils/os_utils.py
cfgutils/sorting.py
cfgutils/transformations.py
cfgutils/angr_utils/__init__.py
cfgutils/angr_utils/ail_block_conv.py
cfgutils/angr_utils/ail_graph_conv.py
cfgutils/angr_utils/block_matcher.py
cfgutils/angr_utils/feat_extractor.py
cfgutils/angr_utils/prettyify_ail.py
cfgutils/data/__init__.py
cfgutils/data/generic_block.py
cfgutils/data/generic_statement.py
cfgutils/hashing/__init__.py
cfgutils/hashing/function_sim_search/__init__.py
cfgutils/hashing/function_sim_search/flowgraph.py
cfgutils/hashing/function_sim_search/sim_hasher.py
cfgutils/matrix/__init__.py
cfgutils/matrix/munkres.py
cfgutils/regions/__init__.py
cfgutils/regions/graph_region.py
cfgutils/regions/region_identifier.py
cfgutils/regions/utils.py
cfgutils/similarity/__init__.py
cfgutils/similarity/block_matcher_base.py
cfgutils/similarity/ged/__init__.py
cfgutils/similarity/ged/abu_aisheh_ged.py
cfgutils/similarity/ged/basque_cfged.py
cfgutils/similarity/ged/hu_cfged.py
cfgutils-1.15.1.dist-info/LICENSE
cfgutils-1.15.1.dist-info/METADATA
cfgutils-1.15.1.dist-info/WHEEL
cfgutils-1.15.1.dist-info/top_level.txt
cfgutils-1.15.1.dist-info/RECORD
