Metadata-Version: 2.1
Name: cfgutils
Version: 1.15.1
Summary: A CFG utility library
Home-page: https://github.com/mahaloz/cfgutils
License: BSD 2 Clause
Classifier: License :: OSI Approved :: BSD License
Classifier: Programming Language :: Python :: 3
Classifier: Programming Language :: Python :: 3.10
Requires-Python: >=3.10
License-File: LICENSE
Requires-Dist: networkx
Requires-Dist: graphviz
Requires-Dist: numpy
Requires-Dist: scipy
Requires-Dist: pygraphviz
Provides-Extra: tests
Requires-Dist: pytest ; extra == 'tests'
Requires-Dist: sailreval ; extra == 'tests'
